celery_amqp_backend/__init__.py
celery_amqp_backend/backend.py
celery_amqp_backend/exceptions.py
celery_amqp_backend-1.2.0.dist-info/LICENSE
celery_amqp_backend-1.2.0.dist-info/METADATA
celery_amqp_backend-1.2.0.dist-info/WHEEL
celery_amqp_backend-1.2.0.dist-info/top_level.txt
celery_amqp_backend-1.2.0.dist-info/RECORD
