Metadata-Version: 2.1
Name: celery-amqp-backend
Version: 1.2.0
Summary: A rewrite of the original Celery AMQP result backend that supports Celery 5.0 and newer.
Home-page: https://github.com/anexia/celery-amqp-backend
Author: Andreas Stocker
Author-email: AStocker@anexia-it.com
License: MIT
Classifier: Development Status :: 5 - Production/Stable
Classifier: Intended Audience :: Developers
Classifier: License :: OSI Approved :: MIT License
Classifier: Operating System :: OS Independent
Classifier: Programming Language :: Python
Classifier: Programming Language :: Python :: 3
Classifier: Programming Language :: Python :: 3.9
Classifier: Programming Language :: Python :: 3.10
Classifier: Programming Language :: Python :: 3.11
Classifier: Programming Language :: Python :: 3.12
Classifier: Framework :: Celery
Classifier: Topic :: Software Development
License-File: LICENSE
Requires-Dist: celery<6.0,>=5.2
